rockervsc/__init__.py
rockervsc/rockervsc.py
rockervsc-0.6.0.dist-info/METADATA
rockervsc-0.6.0.dist-info/WHEEL
rockervsc-0.6.0.dist-info/entry_points.txt
rockervsc-0.6.0.dist-info/licenses/LICENSE
rockervsc-0.6.0.dist-info/RECORD
