Metadata-Version: 2.4
Name: rockervsc
Version: 0.6.0
Summary: A rocker wrapper for launching and attaching vscode to a rocker container
Project-URL: Source, https://github.com/blooop/rockervsc
Project-URL: Home, https://github.com/blooop/rockervsc
Author-email: Austin Gregg-Smith <blooop@gmail.com>
License-Expression: MIT
License-File: LICENSE
Requires-Dist: rockerc[extensions]>=0.7.1
Provides-Extra: test
Requires-Dist: black<=25.1.0,>=23; extra == 'test'
Requires-Dist: coverage<=7.9.1,>=7.5.4; extra == 'test'
Requires-Dist: hypothesis<=6.135.16,>=6.104.2; extra == 'test'
Requires-Dist: pylint<=3.3.7,>=3.2.5; extra == 'test'
Requires-Dist: pytest-cov<=6.2.1,>=4.1; extra == 'test'
Requires-Dist: pytest<=8.4.1,>=7.4; extra == 'test'
Requires-Dist: ruff<=0.12.1,>=0.5.0; extra == 'test'
